dyndict/__init__.py
dyndict/dyndict.py
dyndict/test.py
dyndict-20.7.3.dist-info/LICENSE
dyndict-20.7.3.dist-info/METADATA
dyndict-20.7.3.dist-info/WHEEL
dyndict-20.7.3.dist-info/top_level.txt
dyndict-20.7.3.dist-info/RECORD
