Metadata-Version: 2.1
Name: dyndict
Version: 20.7.3
Summary: Dynamic Dictionary Class
Home-page: https://github.com/hillcrestpaul0719/dyndict
Author: Paul (Kyunghan) Lee
Author-email: contact@paullee.dev
License: UNKNOWN
Platform: UNKNOWN
Classifier: Development Status :: 5 - Production/Stable
Classifier: Programming Language :: Python :: 3
Classifier: License :: OSI Approved :: MIT License
Classifier: Operating System :: OS Independent
Classifier: Intended Audience :: Developers
Classifier: Topic :: Software Development :: Libraries
Classifier: Topic :: Software Development :: Libraries :: Python Modules
Requires-Python: >=3.5
